MANIFEST.in
README.rst
requirements.txt
setup.py
pypptx/__init__.py
pypptx.egg-info/PKG-INFO
pypptx.egg-info/SOURCES.txt
pypptx.egg-info/dependency_links.txt
pypptx.egg-info/entry_points.txt
pypptx.egg-info/requires.txt
pypptx.egg-info/top_level.txt