Metadata-Version: 1.1
Name: pypptx
Version: 0.2.1
Summary: Create a pptx from plain text
Home-page: https://github.com/juanpabloaj/pypptx
Author: JuanPablo AJ
Author-email: jpabloaj@gmail.com
License: MIT
Platform: UNKNOWN
Classifier: Programming Language :: Python
Classifier: Programming Language :: Python :: 2.7
